cppmakelib/__init__.py
cppmakelib/basic/config.py
cppmakelib/builder/cmake.py
cppmakelib/builder/git.py
cppmakelib/builder/include.py
cppmakelib/builder/makefile.py
cppmakelib/compiler/all.py
cppmakelib/compiler/clang.py
cppmakelib/compiler/emcc.py
cppmakelib/compiler/gcc.py
cppmakelib/compiler/msvc.py
cppmakelib/error/config.py
cppmakelib/error/logic.py
cppmakelib/error/subprocess.py
cppmakelib/execution/operation.py
cppmakelib/execution/run.py
cppmakelib/execution/scheduler.py
cppmakelib/file/file_import.py
cppmakelib/file/file_system.py
cppmakelib/logger/compile_commands.py
cppmakelib/logger/module_mapper.py
cppmakelib/logger/module_status.py
cppmakelib/logger/package_status.py
cppmakelib/logger/source_status.py
cppmakelib/logger/unit_preprocess.py
cppmakelib/system/all.py
cppmakelib/system/linux.py
cppmakelib/system/macos.py
cppmakelib/system/windows.py
cppmakelib/unit/executable.py
cppmakelib/unit/header.py
cppmakelib/unit/module.py
cppmakelib/unit/package.py
cppmakelib/unit/source.py
cppmakelib/utility/algorithm.py
cppmakelib/utility/color.py
cppmakelib/utility/decorator.py
cppmakelib/utility/inline.py
cppmakelib/utility/version.py
cppmakelib-127.0.18.dist-info/METADATA
cppmakelib-127.0.18.dist-info/WHEEL
cppmakelib-127.0.18.dist-info/top_level.txt
cppmakelib-127.0.18.dist-info/RECORD
