Metadata-Version: 2.4
Name: cppmakelib
Version: 127.0.18
Summary: A modern C++ builder based on C++20 Modules.
Author-email: shyeyian <shyeyian@icloud.com>
License-Expression: MIT
Requires-Python: >=3.13
